{
  "week": {
    "label": "April 2-9 2026",
    "start_date": "2026-04-02",
    "end_date": "2026-04-09"
  },
  "player_context": {
    "player_name": "PlayerName",
    "gta_plus": false,
    "cash_on_hand": 0,
    "bank_balance": 0,
    "goals_this_week": [
      "make_money",
      "unlock_vehicle"
    ],
    "owned_assets": {
      "properties": [
        "agency",
        "nightclub",
        "ls_car_meet_membership"
      ],
      "businesses": [
        "nightclub",
        "bunker",
        "mc_cocaine",
        "mc_cash"
      ],
      "key_vehicles": [],
      "key_weapons": []
    }
  },
  "weekly_focus": {
    "available_hours": 0,
    "main_goal": "profit",
    "notes": ""
  },
  "weekly_activities": {
    "michael_targets": [
      {
        "name": "Dispatch Work",
        "type": "money_activity",
        "played": false,
        "time_hours": 0,
        "revenue": 0,
        "expenses": 0,
        "notes": ""
      }
    ],
    "trevor_targets": [
      {
        "name": "Heavy Rifle",
        "type": "weapon_or_combat",
        "claimed_or_bought": false,
        "price_paid": 0,
        "value_judgment": "good_pick",
        "notes": ""
      }
    ],
    "franklin_targets": [
      {
        "vehicle_name": "Ocelot Swinger",
        "opportunity_type": "prize_ride",
        "progress": "not_started",
        "result": "pending",
        "buy_price": 0,
        "verdict": "prioritize",
        "notes": ""
      }
    ],
    "lamar_targets": [
      {
        "name": "The Vespucci Job",
        "crew_size": 0,
        "fun_score": 0,
        "team_result": "pending",
        "mvp": "",
        "notes": ""
      }
    ]
  },
  "tony": {
    "nightclub": {
      "owned": true,
      "popularity_percent": 0,
      "safe_cash": 0,
      "technicians_total": 0,
      "technician_assignments": [
        {
          "technician_id": "tech_1",
          "goods_type": "sporting_goods"
        }
      ],
      "goods_stock": [
        {
          "goods_type": "sporting_goods",
          "stock_percent": 0,
          "estimated_value": 0,
          "hours_since_assigned": 0
        }
      ]
    },
    "feeder_businesses": [
      {
        "business_type": "bunker",
        "owned": true,
        "operational": true,
        "supply_level_percent": 0,
        "stock_level_percent": 0,
        "notes": ""
      }
    ],
    "sales_this_week": [
      {
        "goods_type": "sporting_goods",
        "sale_value": 0,
        "session_type": "solo",
        "notes": ""
      }
    ]
  },
  "agent14": {
    "cayo_runs": [
      {
        "run_id": "cayo_01",
        "date": "2026-04-05",
        "players": 1,
        "primary_target": "",
        "secondary_take": 0,
        "safe_cash": 0,
        "gross_take": 0,
        "leader_net": 0,
        "setup_cost": 100000,
        "elite_challenge": false,
        "duration_minutes": 0,
        "result": "success",
        "issues": [],
        "notes": ""
      }
    ],
    "weekly_summary": {
      "total_runs": 0,
      "total_leader_net": 0,
      "best_run_id": "",
      "common_issues": [],
      "notes": ""
    }
  },
  "warnings": [],
  "highlights": []
}